pypdfe/__init__.py
pypdfe/_pypdfe.cp311-win_amd64.pyd
pypdfe-0.1.20.dist-info/LICENSE
pypdfe-0.1.20.dist-info/METADATA
pypdfe-0.1.20.dist-info/WHEEL
pypdfe-0.1.20.dist-info/top_level.txt
pypdfe-0.1.20.dist-info/RECORD
